README.rst
setup.cfg
setup.py
dns_blackhole.egg-info/PKG-INFO
dns_blackhole.egg-info/SOURCES.txt
dns_blackhole.egg-info/dependency_links.txt
dns_blackhole.egg-info/entry_points.txt
dns_blackhole.egg-info/requires.txt
dns_blackhole.egg-info/top_level.txt
dnsblackhole/__init__.py
dnsblackhole/cli.py
etc/blacklist
etc/dns-blackhole.yml
etc/whitelist