Metadata-Version: 1.1
Name: dns-blackhole
Version: 0.12
Summary: A generic DNS black hole zone generator
Home-page: https://github.com/coredumb/dns-blackhole
Author: Olivier Mauras
Author-email: olivier@mauras.ch
License: MIT
Keywords: DNS blackhole
Platform: UNKNOWN
Classifier: Development Status :: 5 - Production/Stable
Classifier: Intended Audience :: System Administrators
Classifier: Topic :: Internet :: Name Service (DNS)
Classifier: License :: OSI Approved :: MIT License
Classifier: Programming Language :: Python :: 2
Classifier: Programming Language :: Python :: 2.7
Classifier: Programming Language :: Python :: 3
Classifier: Programming Language :: Python :: 3.6
